cal_event_search/Form.py
cal_event_search/__init__.py
cal_event_search/api_utils.py
cal_event_search/app.py
cal_event_search/chart_view.py
cal_event_search/events_table.py
cal_event_search-1.2.0.dist-info/LICENSE
cal_event_search-1.2.0.dist-info/METADATA
cal_event_search-1.2.0.dist-info/WHEEL
cal_event_search-1.2.0.dist-info/top_level.txt
cal_event_search-1.2.0.dist-info/RECORD
