Metadata-Version: 2.1
Name: cal-event-search
Version: 1.2.0
Summary: Calendar Event Search
Home-page: https://github.com/polmonroig/calendar_api
Author: Pol Monroig
Author-email: polmonroig@gmail.com
License: UNKNOWN
Platform: UNKNOWN
Classifier: Programming Language :: Python :: 3
Classifier: License :: OSI Approved :: Apache Software License
Classifier: Operating System :: OS Independent
